{
  "$schema": "https://schema.management.azure.com/schemas/2019-04-01/deploymentTemplate.json#",
  "contentVersion": "1.0.0.0",
  "parameters": {
    "Storage.SkuName": {
      "type": "String",
      "defaultValue": "Standard_LRS",
      "metadata": {
        "description": "Provide the pricing tier of the key vault."
      }
    },
    "StorageAccountTableName": {
      "type": "String"
    },
    "Application.Name": {
      "type": "String"
    },
    "Application.Environment": {
      "type": "String"
    },
    "Application.Version": {
      "type": "String"
    },
    "Appication.LinuxFxVersion": {
      "type": "string",
      "defaultValue": "DOTNETCORE|6.0",
      "metadata": {
        "description": "The Runtime stack of current web app"
      }
    },
    "Release.Name": {
      "type": "String",
      "defaultValue": "releasetest"
    },
    "Release.RequestedFor": {
      "type": "String",
      "defaultValue":"lab"
    },
    "Release.SourceCodeBranch": {
      "type": "String",
      "defaultValue": "develop"
    },
    "Release.TriggerType": {
      "type": "String",
      "defaultValue": "Manual"
    },
    "Release.Url": {
      "type": "String",
      "defaultValue": "url"
    },
    "AppSvcPlan.SkuName": {
      "defaultValue": "B1",
      "type": "String",
      "metadata": {
        "description": "Provide the pricing tier of the App Service Plan."
      }
    },
    "Keyvault.SkuName": {
      "defaultValue": "Standard",
      "type": "String",
      "metadata": {
        "description": "Provide the pricing tier of the key vault."
      }
    },
    "Keyvault.TenantId": {
      "type": "String",
      "defaultValue":"xxx"
    },
    "Keyvault.ObjectId": {
      "type": "String",
      "defaultValue": "yyy"
    },
    "Keyvault.SecretName": {
      "type": "String",
      "defaultValue": "EncryptionKey",
      "metadata": {
        "description": "Specifies the name of the secret that you want to create."
      }
    },
    "Keyvault.SecretValue": {
      "type": "SecureString",
      "metadata": {
        "description": "Value of the secret from Key Vault."
      }
    }
  },
    "variables": {
      "KeyVaultName": "[concat(parameters('Application.Name'), '-vault')]",
      "AppServicePlanName": "[concat(parameters('Application.Name'), 'Plan')]",
      "AppServiceName": "[parameters('Application.Name')]",
      "StorageAccountName": "[concat(tolower(replace(parameters('Application.Name'),'-','')), 'storage')]",
      "StorageAccountResourceId": "[resourceId('Microsoft.Storage/storageAccounts', variables('StorageAccountName'))]",
      "Tags": {
        "environment": "[parameters('Application.Environment')]",
        "version": "[parameters('Application.Version')]",
        "releaseName": "[parameters('Release.Name')]",
        "createdBy": "[parameters('Release.Url')]",
        "branch": "[parameters('Release.SourceCodeBranch')]",
        "triggeredBy": "[parameters('Release.RequestedFor')]",
        "triggerType": "[parameters('Release.TriggerType')]"
      }
    },
    "resources": [
      {
        "type": "Microsoft.Resources/tags",
        "apiVersion": "2019-10-01",
        "name": "default",
        "dependsOn": [],
        "properties": {
          "tags": "[variables('Tags')]"
        }
      },
      {
        "type": "Microsoft.Storage/storageAccounts",
        "apiVersion": "2022-05-01",
        "name": "[variables('StorageAccountName')]",
        "location": "[resourceGroup().location]",
        "tags": "[variables('Tags')]",
        "sku": {
          "tier": "Standard",
          "name": "[parameters('Storage.SkuName')]"
        },
        "kind": "StorageV2",
        "properties": {
          "accessTier": "Hot",
          "minimumTlsVersion": "TLS1_2",
          "allowBlobPublicAccess": false,
          "supportsHttpsTrafficOnly": true
        }
      },
      {
        "type": "Microsoft.Storage/storageAccounts/tableServices",
        "apiVersion": "2022-05-01",
        "name": "[concat(variables('storageAccountName'), '/default')]",
        "dependsOn": [
          "[resourceId('Microsoft.Storage/storageAccounts', variables('storageAccountName'))]"
        ],
        "properties": {
          "cors": {
            "corsRules": []
          }
        }
      },
      {
        "type": "Microsoft.Storage/storageAccounts/tableServices/tables",
        "apiVersion": "2022-05-01",
        "name": "[concat(variables('storageAccountName'), '/default/',parameters('StorageAccountTableName'))]",
        "dependsOn": [
          "[resourceId('Microsoft.Storage/storageAccounts/tableServices', variables('storageAccountName'), 'default')]",
          "[resourceId('Microsoft.Storage/storageAccounts', variables('storageAccountName'))]"
        ],
        "properties": {}
      },
      {
        "type": "Microsoft.Web/serverFarms",
        "apiVersion": "2020-06-01",
        "name": "[variables('AppServicePlanName')]",
        "location": "[resourceGroup().location]",
        "tags": "[variables('Tags')]",
        "kind": "linux",
        "sku": {
          "name": "[parameters('AppSvcPlan.SkuName')]",
          "capacity": 1
        },
        "properties": {
          "reserved": true
        }
      },
      {
        "type": "Microsoft.Web/sites",
        "apiVersion": "2020-06-01",
        "name": "[variables('AppServiceName')]",
        "location": "[resourceGroup().location]",
        "kind": "app",
        "dependsOn": [
          "[resourceId('Microsoft.Web/serverfarms', variables('AppServicePlanName'))]"
        ],
        "tags": "[variables('Tags')]",
        "identity": {
          "type": "SystemAssigned"
        },
        "properties": {
          "serverFarmId": "[resourceId('Microsoft.Web/serverFarms', variables('AppServicePlanName'))]",
          "siteConfig": {
            "linuxFxVersion": "[parameters('Appication.LinuxFxVersion')]"
          },
          "resources": [
                  {
                    "type": "config",
                    "name": "appsettings",
                    "apiVersion": "2020-06-01",
                    "dependsOn": [
                      "[resourceId('Microsoft.Web/sites', variables('AppServiceName'))]",
                      "[resourceId('Microsoft.KeyVault/vaults/', variables('keyVaultName'))]",
                      "[resourceId('Microsoft.KeyVault/vaults/secrets', variables('KeyvaultName'), variables('KeyVaultName'))]"
                    ],
                    "properties": {
                      "VaultUri": "[concat('https://',variables('KeyVaultName'),'.vault.azure.net/')]",
                      "StorageAccount.TableName": "[parameters('StorageAccountTableName')]",
                      "Encryption.Key": "[concat('@Microsoft.KeyVault(SecretUri=https://', variables('KeyVaultName'), '.vault.azure.net/secrets/',variables('KeyVaultName'),'/)')]",
                      "WEBSITE_DYNAMIC_CACHE": "0",
                      "WEBSITE_LOCAL_CACHE_OPTION": "Never",
                      "WEBSITE_ENABLE_SYNC_UPDATE_SITE": "true"
                    }
                  },
                  {
                    "type": "config",
                    "name": "connectionstrings",
                    "apiVersion": "2020-06-01",
                    "dependsOn": [
                      "[resourceId('Microsoft.Web/sites', variables('AppServiceName'))]",
                      "[resourceId('Microsoft.Storage/storageAccounts', variables('storageAccountName'))]"
                    ],
                    "properties": {
                      "StorageAccount.ConnectionString": {
                        "value": "[concat('DefaultEndpointsProtocol=https;AccountName=', variables('StorageAccountName'),';AccountKey=', listKeys(variables('StorageAccountResourceId'), '2019-06-01').keys[0].value)]",
                        "type": "Custom"
                      }
                    }
                  }
          ]
        }
      },
      {
      "type": "Microsoft.KeyVault/vaults",
      "name": "[variables('KeyvaultName')]",
      "apiVersion": "2019-09-01",
      "location": "[resourceGroup().location]",
       "tags": "[variables('Tags')]",
      "properties": {
        "enabledForDeployment": true,
        "enabledForTemplateDeployment": true,
        "tenantId": "[parameters('Keyvault.TenantId')]",
        "accessPolicies": [
          {
            "tenantId": "[parameters('Keyvault.TenantId')]",
            "objectId": "[parameters('Keyvault.ObjectId')]",
            "permissions": {
              "keys": [
                "List",
                "Get"
              ],
              "secrets": [
                "List",
                "Get"
              ],
              "certificates": []
            }
          },
          {
            "tenantId": "[parameters('Keyvault.TenantId')]",
            "objectId": "[reference(resourceId('Microsoft.Web/sites', variables('AppServiceName')),'2019-08-01', 'full').identity.principalId]",
            "permissions": {
              "certificates": [],
              "keys": [],
              "secrets": [
                  "get"
                ]
            }
          }
        ],
        "sku": {
          "name": "[parameters('Keyvault.SkuName')]",
          "family": "A"
        }
      },
      "resources": [
            {
              "type": "secrets",
              "name": "[parameters('Keyvault.SecretName')]",
              "apiVersion": "2016-10-01",
              "dependsOn": [
                "[resourceId('Microsoft.KeyVault/vaults/', variables('keyVaultName'))]"
              ],
              "tags": "[variables('Tags')]",
              "properties": {
                "value": "[parameters('Keyvault.SecretValue')]"
              }
            }
      ]
    }
      
    ],
    "outputs": {}
  } 